lib/__init__.py
lib/hello.py
python_simple_package_demo-1.0.0.dist-info/METADATA
python_simple_package_demo-1.0.0.dist-info/WHEEL
python_simple_package_demo-1.0.0.dist-info/top_level.txt
python_simple_package_demo-1.0.0.dist-info/RECORD
